forta_toolkit/__init__.py
forta_toolkit/alerts.py
forta_toolkit/findings.py
forta_toolkit/indexing/__init__.py
forta_toolkit/indexing/parquet.py
forta_toolkit/indexing/pickle.py
forta_toolkit/logging.py
forta_toolkit/parsing/__init__.py
forta_toolkit/parsing/address.py
forta_toolkit/parsing/common.py
forta_toolkit/parsing/env.py
forta_toolkit/parsing/logs.py
forta_toolkit/parsing/traces.py
forta_toolkit/parsing/transaction.py
forta_toolkit/preprocessing.py
forta_toolkit/profiling.py
forta_toolkit/scraping/__init__.py
forta_toolkit-0.4.7.dist-info/METADATA
forta_toolkit-0.4.7.dist-info/WHEEL
forta_toolkit-0.4.7.dist-info/RECORD
